LibHanger/Library/uwConfig.py
LibHanger/Library/uwDeclare.py
LibHanger/Library/uwDialog.py
LibHanger/Library/uwException.py
LibHanger/Library/uwExport.py
LibHanger/Library/uwGetter.py
LibHanger/Library/uwGlobals.py
LibHanger/Library/uwImage.py
LibHanger/Library/uwImport.py
LibHanger/Library/uwLogger.py
LibHanger/Library/uwLoggerMeta.py
LibHanger/Library/uwMail.py
LibHanger/Library/uwMath.py
LibHanger/Library/uwMessage.py
LibHanger/Library/uwPandas.py
LibHanger/Library/uwStringer.py
LibHanger/Library/uwUtil.py
LibHanger/Library/DataAccess/uwPostgres.py
LibHanger/Library/DataAccess/Base/uwDataAccess.py
LibHanger/Models/fields.py
LibHanger/Models/modelFields.py
LibHanger/Models/modelGenerator.py
LibHanger/Models/recset.py
LibHanger/Models/saJoin.py
LibHanger/Models/saOrderBy.py
LibHanger/Models/saWhere.py
LibHanger/Models/Base/BaseDataClass.py
LibHanger/Models/Base/BaseModel.py
LibHanger-1.0.90.dist-info/METADATA
LibHanger-1.0.90.dist-info/WHEEL
LibHanger-1.0.90.dist-info/top_level.txt
LibHanger-1.0.90.dist-info/RECORD
