Metadata-Version: 2.1
Name: LibHanger
Version: 1.0.90
Summary: Common Package
Home-page: https://github.com/kaioman/LibHanger.git
Author: Unchain Works
Author-email: kajin0318@gmail.com
License: BSD-3-Clause
Keywords: ini,inifile
Classifier: Development Status :: 5 - Production/Stable
Classifier: License :: OSI Approved :: BSD License
Classifier: Programming Language :: Python
Classifier: Programming Language :: Python :: 3
Classifier: Programming Language :: Python :: 3.4
Classifier: Programming Language :: Python :: 3.5
Classifier: Programming Language :: Python :: 3.6
Classifier: Programming Language :: Python :: 3.7
Classifier: Programming Language :: Python :: 3.8
Classifier: Programming Language :: Python :: 3.9
Classifier: Topic :: Database
Classifier: Topic :: Software Development :: Libraries :: Python Modules
Requires-Dist: pandas ==1.5.1
Requires-Dist: sqlalchemy ==1.4.44
Requires-Dist: openpyxl ==3.0.10
Requires-Dist: pillow ==9.3.0
Requires-Dist: psycopg2 ==2.9.5
Requires-Dist: psutil ==5.9.4
